async_websocket_client/__init__.py
async_websocket_client/apps.py
async_websocket_client/dispatchers.py
websocket_client_asyncio-1.1.3.dist-info/LICENSE
websocket_client_asyncio-1.1.3.dist-info/METADATA
websocket_client_asyncio-1.1.3.dist-info/WHEEL
websocket_client_asyncio-1.1.3.dist-info/top_level.txt
websocket_client_asyncio-1.1.3.dist-info/RECORD
