Metadata-Version: 2.1
Name: websocket_client_asyncio
Version: 1.1.3
Summary: async_websocket_client
Author: small_shushu
Requires-Python: >=3.7, <4
License-File: LICENSE
Requires-Dist: aioretry
